soundtools/__init__.py
soundtools/soundtools.py
soundtools-0.1.1.dist-info/METADATA
soundtools-0.1.1.dist-info/WHEEL
soundtools-0.1.1.dist-info/top_level.txt
soundtools-0.1.1.dist-info/RECORD
