Metadata-Version: 2.1
Name: soundtools
Version: 0.1.1
Summary: used to work with sounds
Author: Mohammad Erfan Karami
Author-email: erfan012amir016@gmail.com
Classifier: Programming Language :: Python :: 3
Classifier: License :: OSI Approved :: MIT License
Classifier: Operating System :: OS Independent
Requires-Python: >=3.8
